skope_rules_temp/__init__.py
skope_rules_temp/datasets/__init__.py
skope_rules_temp/datasets/credit_data.py
skope_rules_temp/rule.py
skope_rules_temp/skope_rules.py
skope_rules_temp/tests/__init__.py
skope_rules_temp/tests/test_common.py
skope_rules_temp/tests/test_rule.py
skope_rules_temp/tests/test_skope_rules.py
skope_rules_temp/utils.py
skope_rules_temp-0.2.6.dist-info/AUTHORS.rst
skope_rules_temp-0.2.6.dist-info/COPYING
skope_rules_temp-0.2.6.dist-info/METADATA
skope_rules_temp-0.2.6.dist-info/WHEEL
skope_rules_temp-0.2.6.dist-info/RECORD
