Metadata-Version: 2.1
Name: skope-rules-temp
Version: 0.2.6
Summary: Fork of https://github.com/scikit-learn-contrib/skope-rules
Author: Pierre Hulot
Author-email: pierre@ai-vidence.com
Requires-Python: >=3.10
Classifier: Programming Language :: Python :: 3
Classifier: Programming Language :: Python :: 3.10
Classifier: Programming Language :: Python :: 3.11
Classifier: Programming Language :: Python :: 3.12
Requires-Dist: numpy (>=1.26.4,<2.0.0)
Requires-Dist: numpydoc (>=1.6.0,<2.0.0)
Requires-Dist: pandas (>=2.2.0,<3.0.0)
Requires-Dist: scikit-learn (>=1.4.1.post1,<2.0.0)
Requires-Dist: scipy (>=1.0.0)
Requires-Dist: sphinx-gallery (>=0.15.0,<0.16.0)
Requires-Dist: xlrd (>=2.0.1,<3.0.0)
